orderedmultidict/__init__.py
orderedmultidict/__version__.py
orderedmultidict/itemlist.py
orderedmultidict/orderedmultidict.py
orderedmultidict/py.typed
orderedmultidict-1.0.2.dist-info/LICENSE.md
orderedmultidict-1.0.2.dist-info/METADATA
orderedmultidict-1.0.2.dist-info/WHEEL
orderedmultidict-1.0.2.dist-info/top_level.txt
orderedmultidict-1.0.2.dist-info/RECORD
